gevent/__init__.py
gevent/_abstract_linkable.py
gevent/_compat.py
gevent/_config.py
gevent/_fileobjectcommon.py
gevent/_fileobjectposix.py
gevent/_gevent_c_abstract_linkable.cpython-313-aarch64-linux-musl.so
gevent/_gevent_c_greenlet_primitives.cpython-313-aarch64-linux-musl.so
gevent/_gevent_c_hub_local.cpython-313-aarch64-linux-musl.so
gevent/_gevent_c_hub_primitives.cpython-313-aarch64-linux-musl.so
gevent/_gevent_c_ident.cpython-313-aarch64-linux-musl.so
gevent/_gevent_c_imap.cpython-313-aarch64-linux-musl.so
gevent/_gevent_c_semaphore.cpython-313-aarch64-linux-musl.so
gevent/_gevent_c_tracer.cpython-313-aarch64-linux-musl.so
gevent/_gevent_c_waiter.cpython-313-aarch64-linux-musl.so
gevent/_gevent_cevent.cpython-313-aarch64-linux-musl.so
gevent/_gevent_cgreenlet.cpython-313-aarch64-linux-musl.so
gevent/_gevent_clocal.cpython-313-aarch64-linux-musl.so
gevent/_gevent_cqueue.cpython-313-aarch64-linux-musl.so
gevent/_greenlet_primitives.py
gevent/_hub_local.py
gevent/_hub_primitives.py
gevent/_ident.py
gevent/_imap.py
gevent/_interfaces.py
gevent/_monitor.py
gevent/_patcher.py
gevent/_semaphore.py
gevent/_socket3.py
gevent/_socketcommon.py
gevent/_tblib.py
gevent/_threading.py
gevent/_tracer.py
gevent/_util.py
gevent/_waiter.py
gevent/ares.py
gevent/backdoor.py
gevent/baseserver.py
gevent/builtins.py
gevent/contextvars.py
gevent/core.py
gevent/event.py
gevent/events.py
gevent/exceptions.py
gevent/fileobject.py
gevent/greenlet.py
gevent/hub.py
gevent/local.py
gevent/lock.py
gevent/os.py
gevent/pool.py
gevent/pywsgi.py
gevent/queue.py
gevent/resolver_ares.py
gevent/resolver_thread.py
gevent/select.py
gevent/selectors.py
gevent/server.py
gevent/signal.py
gevent/socket.py
gevent/ssl.py
gevent/subprocess.py
gevent/thread.py
gevent/threading.py
gevent/threadpool.py
gevent/time.py
gevent/timeout.py
gevent/util.py
gevent/win32util.py
gevent/_ffi/__init__.py
gevent/_ffi/callback.py
gevent/_ffi/loop.py
gevent-25.8.2.dist-info/METADATA
gevent-25.8.2.dist-info/WHEEL
gevent-25.8.2.dist-info/entry_points.txt
gevent-25.8.2.dist-info/top_level.txt
gevent-25.8.2.dist-info/RECORD
gevent-25.8.2.dist-info/licenses/LICENSE
