Metadata-Version: 2.4
Name: gevent
Version: 25.8.2
Summary: Coroutine-based network library
Home-page: http://www.gevent.org/
Author: Denis Bilenko
Author-email: denis.bilenko@gmail.com
Maintainer: Jason Madden
Maintainer-email: jason@seecoresoftware.com
License: MIT
Project-URL: Bug Tracker, https://github.com/gevent/gevent/issues
Project-URL: Source Code, https://github.com/gevent/gevent/
Project-URL: Documentation, http://www.gevent.org
Project-URL: Changes, https://www.gevent.org/changelog.html
Keywords: greenlet coroutine cooperative multitasking light threads monkey
Classifier: Programming Language :: Python :: 3 :: Only
Classifier: Programming Language :: Python :: 3.9
Classifier: Programming Language :: Python :: 3.10
Classifier: Programming Language :: Python :: 3.11
Classifier: Programming Language :: Python :: 3.12
Classifier: Programming Language :: Python :: 3.13
Classifier: Programming Language :: Python :: Implementation :: CPython
Classifier: Programming Language :: Python :: Implementation :: PyPy
Classifier: Operating System :: MacOS :: MacOS X
Classifier: Operating System :: POSIX
Classifier: Operating System :: Microsoft :: Windows
Classifier: Topic :: Internet
Classifier: Topic :: Software Development :: Libraries :: Python Modules
Classifier: Intended Audience :: Developers
Classifier: Development Status :: 4 - Beta
Requires-Python: >=3.9
License-File: LICENSE
Requires-Dist: greenlet>=3.2.2; platform_python_implementation == "CPython"
Requires-Dist: cffi>=1.17.1; platform_python_implementation == "CPython" and sys_platform == "win32"
Requires-Dist: zope.event
Requires-Dist: zope.interface
Provides-Extra: dnspython
Requires-Dist: dnspython<2.0,>=1.16.0; python_version < "3.10" and extra == "dnspython"
Requires-Dist: idna; python_version < "3.10" and extra == "dnspython"
Provides-Extra: events
Provides-Extra: monitor
Requires-Dist: psutil>=5.7.0; (sys_platform != "win32" or platform_python_implementation == "CPython") and extra == "monitor"
Provides-Extra: recommended
Requires-Dist: cffi>=1.17.1; platform_python_implementation == "CPython" and extra == "recommended"
Requires-Dist: dnspython<2.0,>=1.16.0; python_version < "3.10" and extra == "recommended"
Requires-Dist: idna; python_version < "3.10" and extra == "recommended"
Requires-Dist: psutil>=5.7.0; (sys_platform != "win32" or platform_python_implementation == "CPython") and extra == "recommended"
Provides-Extra: docs
Requires-Dist: sphinx; extra == "docs"
Requires-Dist: furo; extra == "docs"
Requires-Dist: repoze.sphinx.autointerface; extra == "docs"
Requires-Dist: sphinxcontrib-programoutput; extra == "docs"
Requires-Dist: zope.schema; extra == "docs"
Provides-Extra: test
Requires-Dist: cffi>=1.17.1; platform_python_implementation == "CPython" and extra == "test"
Requires-Dist: dnspython<2.0,>=1.16.0; python_version < "3.10" and extra == "test"
Requires-Dist: idna; python_version < "3.10" and extra == "test"
Requires-Dist: psutil>=5.7.0; (sys_platform != "win32" or platform_python_implementation == "CPython") and extra == "test"
Requires-Dist: requests; extra == "test"
Requires-Dist: coverage>=5.0; sys_platform != "win32" and extra == "test"
Requires-Dist: objgraph; extra == "test"
Dynamic: author
Dynamic: author-email
Dynamic: classifier
Dynamic: description
Dynamic: home-page
Dynamic: keywords
Dynamic: license
Dynamic: license-file
Dynamic: maintainer
Dynamic: maintainer-email
Dynamic: project-url
Dynamic: provides-extra
Dynamic: requires-dist
Dynamic: requires-python
Dynamic: summary
